odoo/addons/sm_rewards/__init__.py
odoo/addons/sm_rewards/__manifest__.py
odoo/addons/sm_rewards/email_tmpl/cs_reward_completed_email.xml
odoo/addons/sm_rewards/email_tmpl/cs_reward_soci_not_found_email.xml
odoo/addons/sm_rewards/models/__init__.py
odoo/addons/sm_rewards/models/models_cs_car_service.py
odoo/addons/sm_rewards/models/models_cs_task.py
odoo/addons/sm_rewards/models/models_pocketbook_record.py
odoo/addons/sm_rewards/models/models_sm_company.py
odoo/addons/sm_rewards/models/models_sm_member.py
odoo/addons/sm_rewards/models/models_sm_res_config_settings.py
odoo/addons/sm_rewards/models/models_sm_reward.py
odoo/addons/sm_rewards/models/models_sm_reward_cron.py
odoo/addons/sm_rewards/models/models_smp_carsharing_registration_request.py
odoo/addons/sm_rewards/models/models_smp_carsharing_tariff.py
odoo/addons/sm_rewards/models/models_smp_reservation_compute.py
odoo/addons/sm_rewards/security/ir.model.access.csv
odoo/addons/sm_rewards/views/views_cron.xml
odoo/addons/sm_rewards/views/views_cs_car_service.xml
odoo/addons/sm_rewards/views/views_cs_registration_request.xml
odoo/addons/sm_rewards/views/views_cs_task.xml
odoo/addons/sm_rewards/views/views_members.xml
odoo/addons/sm_rewards/views/views_pocketbook_record.xml
odoo/addons/sm_rewards/views/views_res_config_settings.xml
odoo/addons/sm_rewards/views/views_reservation_compute.xml
odoo/addons/sm_rewards/views/views_reward.xml
odoo/addons/sm_rewards/views/views_reward_actions.xml
odoo/addons/sm_rewards/views/views_tariff.xml
odoo12_addon_sm_rewards-12.0.0.0.15.dist-info/METADATA
odoo12_addon_sm_rewards-12.0.0.0.15.dist-info/WHEEL
odoo12_addon_sm_rewards-12.0.0.0.15.dist-info/top_level.txt
odoo12_addon_sm_rewards-12.0.0.0.15.dist-info/RECORD
