Metadata-Version: 2.1
Name: odoo12-addon-sm-rewards
Version: 12.0.0.0.15
Summary: sm_rewards
Home-page: http://www.sommobilitat.coop
Author: Som Mobilitat
Classifier: Programming Language :: Python
Classifier: Framework :: Odoo
Classifier: Framework :: Odoo :: 12.0
Requires-Python: >=3.5
Requires-Dist: odoo12-addon-sm-partago-tariffs
Requires-Dist: odoo12-addon-sm-partago-usage
Requires-Dist: odoo12-addon-sm-partago-user
Requires-Dist: odoo12-addon-sm-pocketbook
Requires-Dist: odoo12-addon-vertical-carsharing
Requires-Dist: odoo (<12.1dev,>=12.0a)
